modrc/__init__.py
modrc/__main__.py
modrc/exceptions.py
modrc-0.4.1.dist-info/LICENSE.txt
modrc-0.4.1.dist-info/METADATA
modrc-0.4.1.dist-info/WHEEL
modrc-0.4.1.dist-info/entry_points.txt
modrc-0.4.1.dist-info/top_level.txt
modrc-0.4.1.dist-info/RECORD
