Metadata-Version: 2.1
Name: modrc
Version: 0.4.1
Summary: The CLI to make managing your config files across systems easier.
Home-page: UNKNOWN
License: MIT
Keywords: cli dotfiles config
Platform: UNKNOWN
Classifier: Development Status :: 3 - Alpha
Classifier: Environment :: Console
Classifier: Intended Audience :: Developers
Classifier: License :: OSI Approved :: MIT License
Classifier: Programming Language :: Python :: 3.5
Classifier: Programming Language :: Python :: 3.6
Classifier: Programming Language :: Python :: 3.7
Classifier: Programming Language :: Python :: 3.8
Classifier: Topic :: Utilities
Requires-Dist: click
Requires-Dist: distro
Requires-Dist: pyyaml
